[
  {
    "name": "Hossomaki Pepino Kappa Maki ST MARCHE",
    "market": "StMarche",
    "price": 1335,
    "extraction_date": "2025-09-21T19:58:58.928325",
    "category": "Sushi e Sashimi",
    "brand": null,
    "product_url": "https://marche.com.br/collections/pratos-prontos-1/products/hossomaki-pepino-kappa-maki-st-marche",
    "source_id": null,
    "quantity": 0.15,
    "unit_of_measure": "KG",
    "extraction_url": "https://marche.com.br/collections/sushi-e-sashimi?store_id=66677604431&page=1",
    "id": 625032502267871232,
    "created_at": null,
    "discounts": [],
    "currency": "BRL"
  },
  {
    "name": "Jhow De Salmão ST MARCHE",
    "market": "StMarche",
    "price": 2399,
    "extraction_date": "2025-09-21T19:58:58.928325",
    "category": "Sushi e Sashimi",
    "brand": null,
    "product_url": "https://marche.com.br/collections/pratos-prontos-1/products/jhow-de-salmao-st-marche",
    "source_id": null,
    "quantity": 0.15,
    "unit_of_measure": "KG",
    "extraction_url": "https://marche.com.br/collections/sushi-e-sashimi?store_id=66677604431&page=1",
    "id": 625032502267871233,
    "created_at": null,
    "discounts": [],
    "currency": "BRL"
  },
  {
    "name": "Hossomaki De Salmão ST MARCHE",
    "market": "StMarche",
    "price": 2249,
    "extraction_date": "2025-09-21T19:58:58.928325",
    "category": "Sushi e Sashimi",
    "brand": null,
    "product_url": "https://marche.com.br/collections/pratos-prontos-1/products/hossomaki-de-salmao-st-marche",
    "source_id": null,
    "quantity": 0.15,
    "unit_of_measure": "KG",
    "extraction_url": "https://marche.com.br/collections/sushi-e-sashimi?store_id=66677604431&page=1",
    "id": 625032502267871234,
    "created_at": null,
    "discounts": [],
    "currency": "BRL"
  },
  {
    "name": "Jhow de Salmão Sem Cream Cheese ST MARCHE",
    "market": "StMarche",
    "price": 2699,
    "extraction_date": "2025-09-21T19:58:58.928325",
    "category": "Sushi e Sashimi",
    "brand": null,
    "product_url": "https://marche.com.br/collections/pratos-prontos-1/products/jhow-de-salmao-sem-cream-cheese-st-marche",
    "source_id": null,
    "quantity": 0.15,
    "unit_of_measure": "KG",
    "extraction_url": "https://marche.com.br/collections/sushi-e-sashimi?store_id=66677604431&page=1",
    "id": 625032502267871235,
    "created_at": null,
    "discounts": [],
    "currency": "BRL"
  },
  {
    "name": "Sashimi Misto ST MARCHE",
    "market": "StMarche",
    "price": 2590,
    "extraction_date": "2025-09-21T19:58:58.928325",
    "category": "Sushi e Sashimi",
    "brand": null,
    "product_url": "https://marche.com.br/collections/pratos-prontos-1/products/sashimi-misto-st-marche",
    "source_id": null,
    "quantity": 0.16,
    "unit_of_measure": "KG",
    "extraction_url": "https://marche.com.br/collections/sushi-e-sashimi?store_id=66677604431&page=1",
    "id": 625032502272065536,
    "created_at": null,
    "discounts": [],
    "currency": "BRL"
  },
  {
    "name": "Uramaki de Salmão ST MARCHE",
    "market": "StMarche",
    "price": 2208,
    "extraction_date": "2025-09-21T19:58:58.928325",
    "category": "Sushi e Sashimi",
    "brand": null,
    "product_url": "https://marche.com.br/collections/pratos-prontos-1/products/uramaki-de-salmao-st-marche",
    "source_id": null,
    "quantity": 0.17,
    "unit_of_measure": "KG",
    "extraction_url": "https://marche.com.br/collections/sushi-e-sashimi?store_id=66677604431&page=1",
    "id": 625032502272065537,
    "created_at": null,
    "discounts": [],
    "currency": "BRL"
  },
  {
    "name": "California Roll ST MARCHE",
    "market": "StMarche",
    "price": 1410,
    "extraction_date": "2025-09-21T19:58:58.928325",
    "category": "Sushi e Sashimi",
    "brand": null,
    "product_url": "https://marche.com.br/collections/pratos-prontos-1/products/california-roll-st-marche",
    "source_id": null,
    "quantity": 0.15,
    "unit_of_measure": "KG",
    "extraction_url": "https://marche.com.br/collections/sushi-e-sashimi?store_id=66677604431&page=1",
    "id": 625032502272065538,
    "created_at": null,
    "discounts": [],
    "currency": "BRL"
  },
  {
    "name": "Niguri Salmão Maçaricado ST MARCHE",
    "market": "StMarche",
    "price": 2399,
    "extraction_date": "2025-09-21T19:58:58.928325",
    "category": "Sushi e Sashimi",
    "brand": null,
    "product_url": "https://marche.com.br/collections/pratos-prontos-1/products/niguri-salmao-macaricado-st-marche",
    "source_id": null,
    "quantity": 0.15,
    "unit_of_measure": "KG",
    "extraction_url": "https://marche.com.br/collections/sushi-e-sashimi?store_id=66677604431&page=1",
    "id": 625032502272065539,
    "created_at": null,
    "discounts": [],
    "currency": "BRL"
  },
  {
    "name": "Uramaki de Salmão Skin ST MARCHE",
    "market": "StMarche",
    "price": 2208,
    "extraction_date": "2025-09-21T19:58:58.928325",
    "category": "Sushi e Sashimi",
    "brand": null,
    "product_url": "https://marche.com.br/collections/pratos-prontos-1/products/uramaki-de-salmao-skin-st-marche",
    "source_id": null,
    "quantity": 0.17,
    "unit_of_measure": "KG",
    "extraction_url": "https://marche.com.br/collections/sushi-e-sashimi?store_id=66677604431&page=1",
    "id": 625032502276259840,
    "created_at": null,
    "discounts": [],
    "currency": "BRL"
  },
  {
    "name": "Sashimi de Salmão ST MARCHE",
    "market": "StMarche",
    "price": 5597,
    "extraction_date": "2025-09-21T19:58:58.928325",
    "category": "Sushi e Sashimi",
    "brand": null,
    "product_url": "https://marche.com.br/collections/pratos-prontos-1/products/sashimi-de-salmao-st-marche",
    "source_id": null,
    "quantity": 0.28,
    "unit_of_measure": "KG",
    "extraction_url": "https://marche.com.br/collections/sushi-e-sashimi?store_id=66677604431&page=1",
    "id": 625032502276259841,
    "created_at": null,
    "discounts": [],
    "currency": "BRL"
  },
  {
    "name": "Sashimi de Atum ST MARCHE",
    "market": "StMarche",
    "price": 2339,
    "extraction_date": "2025-09-21T19:58:58.928325",
    "category": "Sushi e Sashimi",
    "brand": null,
    "product_url": "https://marche.com.br/collections/pratos-prontos-1/products/sashimi-de-atum-st-marche",
    "source_id": null,
    "quantity": 0.13,
    "unit_of_measure": "KG",
    "extraction_url": "https://marche.com.br/collections/sushi-e-sashimi?store_id=66677604431&page=1",
    "id": 625032502276259842,
    "created_at": null,
    "discounts": [],
    "currency": "BRL"
  },
  {
    "name": "Batera de Salmão ST MARCHE",
    "market": "StMarche",
    "price": 4722,
    "extraction_date": "2025-09-21T19:58:58.928325",
    "category": "Sushi e Sashimi",
    "brand": null,
    "product_url": "https://marche.com.br/collections/pratos-prontos-1/products/batera-de-salmao-st-marche",
    "source_id": null,
    "quantity": 0.315,
    "unit_of_measure": "KG",
    "extraction_url": "https://marche.com.br/collections/sushi-e-sashimi?store_id=66677604431&page=1",
    "id": 625032502276259843,
    "created_at": null,
    "discounts": [],
    "currency": "BRL"
  },
  {
    "name": "Niguiri de Salmão ST MARCHE",
    "market": "StMarche",
    "price": 2878,
    "extraction_date": "2025-09-21T19:58:58.928325",
    "category": "Sushi e Sashimi",
    "brand": null,
    "product_url": "https://marche.com.br/collections/pratos-prontos-1/products/niguiri-de-salmao-st-marche",
    "source_id": null,
    "quantity": 0.18,
    "unit_of_measure": "KG",
    "extraction_url": "https://marche.com.br/collections/sushi-e-sashimi?store_id=66677604431&page=1",
    "id": 625032502276259844,
    "created_at": null,
    "discounts": [],
    "currency": "BRL"
  }
]